[{"id":"log-of-unexplained-locations-jp:10000","designation":"10000","url":"http://scp-jp.wikidot.com/log-of-unexplained-locations-jp:10000"},{"id":"log-of-unexplained-locations-jp:10001","designation":"10001","url":"http://scp-jp.wikidot.com/log-of-unexplained-locations-jp:10001"},{"id":"log-of-unexplained-locations-jp:10003","designation":"10003","url":"http://scp-jp.wikidot.com/log-of-unexplained-locations-jp:10003"},{"id":"log-of-unexplained-locations-jp:10004","designation":"10004","url":"http://scp-jp.wikidot.com/log-of-unexplained-locations-jp:10004"},{"id":"log-of-unexplained-locations-jp:10005","designation":"10005","url":"http://scp-jp.wikidot.com/log-of-unexplained-locations-jp:10005"},{"id":"log-of-unexplained-locations-jp:10006","designation":"10006","url":"http://scp-jp.wikidot.com/log-of-unexplained-locations-jp:10006"},{"id":"log-of-unexplained-locations-jp:10007","designation":"10007","url":"http://scp-jp.wikidot.com/log-of-unexplained-locations-jp:10007"},{"id":"log-of-unexplained-locations-jp:10008","designation":"10008","url":"http://scp-jp.wikidot.com/log-of-unexplained-locations-jp:10008"},{"id":"log-of-unexplained-locations-jp:10009","designation":"10009","url":"http://scp-jp.wikidot.com/log-of-unexplained-locations-jp:10009"},{"id":"log-of-unexplained-locations-jp:10010","designation":"10010","url":"http://scp-jp.wikidot.com/log-of-unexplained-locations-jp:10010"},{"id":"log-of-unexplained-locations-jp:10012","designation":"10012","url":"http://scp-jp.wikidot.com/log-of-unexplained-locations-jp:10012"},{"id":"log-of-unexplained-locations-jp:10013","designation":"10013","url":"http://scp-jp.wikidot.com/log-of-unexplained-locations-jp:10013"},{"id":"log-of-unexplained-locations-jp:10014","designation":"10014","url":"http://scp-jp.wikidot.com/log-of-unexplained-locations-jp:10014"},{"id":"log-of-unexplained-locations-jp:10015","designation":"10015","url":"http://scp-jp.wikidot.com/log-of-unexplained-locations-jp:10015"},{"id":"log-of-unexplained-locations-jp:10016","designation":"10016","url":"http://scp-jp.wikidot.com/log-of-unexplained-locations-jp:10016"},{"id":"log-of-unexplained-locations-jp:10017","designation":"10017","url":"http://scp-jp.wikidot.com/log-of-unexplained-locations-jp:10017"},{"id":"log-of-unexplained-locations-jp:10018","designation":"10018","url":"http://scp-jp.wikidot.com/log-of-unexplained-locations-jp:10018"},{"id":"log-of-unexplained-locations-jp:10020","designation":"10020","url":"http://scp-jp.wikidot.com/log-of-unexplained-locations-jp:10020"},{"id":"log-of-unexplained-locations-jp:10024","designation":"10024","url":"http://scp-jp.wikidot.com/log-of-unexplained-locations-jp:10024"},{"id":"log-of-unexplained-locations-jp:10026","designation":"10026","url":"http://scp-jp.wikidot.com/log-of-unexplained-locations-jp:10026"},{"id":"log-of-unexplained-locations-jp:10030","designation":"10030","url":"http://scp-jp.wikidot.com/log-of-unexplained-locations-jp:10030"},{"id":"log-of-unexplained-locations-jp:10031","designation":"10031","url":"http://scp-jp.wikidot.com/log-of-unexplained-locations-jp:10031"},{"id":"log-of-unexplained-locations-jp:10032","designation":"10032","url":"http://scp-jp.wikidot.com/log-of-unexplained-locations-jp:10032"},{"id":"log-of-unexplained-locations-jp:10034","designation":"10034","url":"http://scp-jp.wikidot.com/log-of-unexplained-locations-jp:10034"},{"id":"log-of-unexplained-locations-jp:10035","designation":"10035","url":"http://scp-jp.wikidot.com/log-of-unexplained-locations-jp:10035"},{"id":"log-of-unexplained-locations-jp:10037","designation":"10037","url":"http://scp-jp.wikidot.com/log-of-unexplained-locations-jp:10037"},{"id":"log-of-unexplained-locations-jp:10038","designation":"10038","url":"http://scp-jp.wikidot.com/log-of-unexplained-locations-jp:10038"},{"id":"log-of-unexplained-locations-jp:10040","designation":"10040","url":"http://scp-jp.wikidot.com/log-of-unexplained-locations-jp:10040"},{"id":"log-of-unexplained-locations-jp:10042","designation":"10042","url":"http://scp-jp.wikidot.com/log-of-unexplained-locations-jp:10042"},{"id":"log-of-unexplained-locations-jp:10043","designation":"10043","url":"http://scp-jp.wikidot.com/log-of-unexplained-locations-jp:10043"},{"id":"log-of-unexplained-locations-jp:10045","designation":"10045","url":"http://scp-jp.wikidot.com/log-of-unexplained-locations-jp:10045"},{"id":"log-of-unexplained-locations-jp:10048","designation":"10048","url":"http://scp-jp.wikidot.com/log-of-unexplained-locations-jp:10048"},{"id":"log-of-unexplained-locations-jp:10050","designation":"10050","url":"http://scp-jp.wikidot.com/log-of-unexplained-locations-jp:10050"},{"id":"log-of-unexplained-locations-jp:10052","designation":"10052","url":"http://scp-jp.wikidot.com/log-of-unexplained-locations-jp:10052"},{"id":"log-of-unexplained-locations-jp:10053","designation":"10053","url":"http://scp-jp.wikidot.com/log-of-unexplained-locations-jp:10053"},{"id":"log-of-unexplained-locations-jp:10055","designation":"10055","url":"http://scp-jp.wikidot.com/log-of-unexplained-locations-jp:10055"},{"id":"log-of-unexplained-locations-jp:10056","designation":"10056","url":"http://scp-jp.wikidot.com/log-of-unexplained-locations-jp:10056"},{"id":"log-of-unexplained-locations-jp:10057","designation":"10057","url":"http://scp-jp.wikidot.com/log-of-unexplained-locations-jp:10057"},{"id":"log-of-unexplained-locations-jp:10058","designation":"10058","url":"http://scp-jp.wikidot.com/log-of-unexplained-locations-jp:10058"},{"id":"log-of-unexplained-locations-jp:10060","designation":"10060","url":"http://scp-jp.wikidot.com/log-of-unexplained-locations-jp:10060"},{"id":"log-of-unexplained-locations-jp:10061","designation":"10061","url":"http://scp-jp.wikidot.com/log-of-unexplained-locations-jp:10061"},{"id":"log-of-unexplained-locations-jp:10062","designation":"10062","url":"http://scp-jp.wikidot.com/log-of-unexplained-locations-jp:10062"},{"id":"log-of-unexplained-locations-jp:10063","designation":"10063","url":"http://scp-jp.wikidot.com/log-of-unexplained-locations-jp:10063"},{"id":"log-of-unexplained-locations-jp:10066","designation":"10066","url":"http://scp-jp.wikidot.com/log-of-unexplained-locations-jp:10066"},{"id":"log-of-unexplained-locations-jp:10067","designation":"10067","url":"http://scp-jp.wikidot.com/log-of-unexplained-locations-jp:10067"},{"id":"log-of-unexplained-locations-jp:10068","designation":"10068","url":"http://scp-jp.wikidot.com/log-of-unexplained-locations-jp:10068"},{"id":"log-of-unexplained-locations-jp:10069","designation":"10069","url":"http://scp-jp.wikidot.com/log-of-unexplained-locations-jp:10069"},{"id":"log-of-unexplained-locations-jp:10070","designation":"10070","url":"http://scp-jp.wikidot.com/log-of-unexplained-locations-jp:10070"},{"id":"log-of-unexplained-locations-jp:10073","designation":"10073","url":"http://scp-jp.wikidot.com/log-of-unexplained-locations-jp:10073"},{"id":"log-of-unexplained-locations-jp:10074","designation":"10074","url":"http://scp-jp.wikidot.com/log-of-unexplained-locations-jp:10074"},{"id":"log-of-unexplained-locations-jp:10075","designation":"10075","url":"http://scp-jp.wikidot.com/log-of-unexplained-locations-jp:10075"},{"id":"log-of-unexplained-locations-jp:10077","designation":"10077","url":"http://scp-jp.wikidot.com/log-of-unexplained-locations-jp:10077"},{"id":"log-of-unexplained-locations-jp:10078","designation":"10078","url":"http://scp-jp.wikidot.com/log-of-unexplained-locations-jp:10078"},{"id":"log-of-unexplained-locations-jp:10079","designation":"10079","url":"http://scp-jp.wikidot.com/log-of-unexplained-locations-jp:10079"},{"id":"log-of-unexplained-locations-jp:10081","designation":"10081","url":"http://scp-jp.wikidot.com/log-of-unexplained-locations-jp:10081"},{"id":"log-of-unexplained-locations-jp:10082","designation":"10082","url":"http://scp-jp.wikidot.com/log-of-unexplained-locations-jp:10082"},{"id":"log-of-unexplained-locations-jp:10083","designation":"10083","url":"http://scp-jp.wikidot.com/log-of-unexplained-locations-jp:10083"},{"id":"log-of-unexplained-locations-jp:10084","designation":"10084","url":"http://scp-jp.wikidot.com/log-of-unexplained-locations-jp:10084"},{"id":"log-of-unexplained-locations-jp:10085","designation":"10085","url":"http://scp-jp.wikidot.com/log-of-unexplained-locations-jp:10085"},{"id":"log-of-unexplained-locations-jp:10086","designation":"10086","url":"http://scp-jp.wikidot.com/log-of-unexplained-locations-jp:10086"},{"id":"log-of-unexplained-locations-jp:10087","designation":"10087","url":"http://scp-jp.wikidot.com/log-of-unexplained-locations-jp:10087"},{"id":"log-of-unexplained-locations-jp:10088","designation":"10088","url":"http://scp-jp.wikidot.com/log-of-unexplained-locations-jp:10088"},{"id":"log-of-unexplained-locations-jp:10089","designation":"10089","url":"http://scp-jp.wikidot.com/log-of-unexplained-locations-jp:10089"},{"id":"log-of-unexplained-locations-jp:10091","designation":"10091","url":"http://scp-jp.wikidot.com/log-of-unexplained-locations-jp:10091"},{"id":"log-of-unexplained-locations-jp:10093","designation":"10093","url":"http://scp-jp.wikidot.com/log-of-unexplained-locations-jp:10093"},{"id":"log-of-unexplained-locations-jp:10094","designation":"10094","url":"http://scp-jp.wikidot.com/log-of-unexplained-locations-jp:10094"},{"id":"log-of-unexplained-locations-jp:10095","designation":"10095","url":"http://scp-jp.wikidot.com/log-of-unexplained-locations-jp:10095"},{"id":"log-of-unexplained-locations-jp:10096","designation":"10096","url":"http://scp-jp.wikidot.com/log-of-unexplained-locations-jp:10096"},{"id":"log-of-unexplained-locations-jp:10097","designation":"10097","url":"http://scp-jp.wikidot.com/log-of-unexplained-locations-jp:10097"},{"id":"log-of-unexplained-locations-jp:10098","designation":"10098","url":"http://scp-jp.wikidot.com/log-of-unexplained-locations-jp:10098"},{"id":"log-of-unexplained-locations-jp:10100","designation":"10100","url":"http://scp-jp.wikidot.com/log-of-unexplained-locations-jp:10100"},{"id":"log-of-unexplained-locations-jp:10101","designation":"10101","url":"http://scp-jp.wikidot.com/log-of-unexplained-locations-jp:10101"},{"id":"log-of-unexplained-locations-jp:10102","designation":"10102","url":"http://scp-jp.wikidot.com/log-of-unexplained-locations-jp:10102"},{"id":"log-of-unexplained-locations-jp:10104","designation":"10104","url":"http://scp-jp.wikidot.com/log-of-unexplained-locations-jp:10104"},{"id":"log-of-unexplained-locations-jp:10105","designation":"10105","url":"http://scp-jp.wikidot.com/log-of-unexplained-locations-jp:10105"}]